byted_tuna_op_core/__init__.py
byted_tuna_op_core-0.0.1.dist-info/METADATA
byted_tuna_op_core-0.0.1.dist-info/WHEEL
byted_tuna_op_core-0.0.1.dist-info/top_level.txt
byted_tuna_op_core-0.0.1.dist-info/RECORD
