Metadata-Version: 2.1
Name: byted-tuna-op-core
Version: 0.0.1
Summary: A simple package named byted_tuna_op_core
Home-page: https://github.com/artifact/byted_tuna_op_core.git
Author: artifact
Author-email: artifact@example.com
License: UNKNOWN
Platform: UNKNOWN
Classifier: Programming Language :: Python :: 3
Classifier: License :: OSI Approved :: MIT License
Classifier: Operating System :: OS Independent
